supertask/__init__.py
supertask/cli.py
supertask/core.py
supertask/model.py
supertask/util.py
supertask/http/__init__.py
supertask/http/routes.py
supertask/http/service.py
supertask/provision/__init__.py
supertask/provision/database.py
supertask/provision/seeder.py
supertask/store/__init__.py
supertask/store/cratedb.py
supertask/store/mongodb.py
supertask/vendor/__init__.py
supertask/vendor/jobs.py
supertask-0.0.0.dev0.dist-info/licenses/LICENSE
supertask-0.0.0.dev0.dist-info/METADATA
supertask-0.0.0.dev0.dist-info/WHEEL
supertask-0.0.0.dev0.dist-info/entry_points.txt
supertask-0.0.0.dev0.dist-info/top_level.txt
supertask-0.0.0.dev0.dist-info/RECORD
