Metadata-Version: 2.4
Name: supertask
Version: 0.0.0.dev0
Summary: A convenience job scheduler.
Author-email: Walter Behmann <walter@crate.io>, Andreas Motl <andreas.motl@crate.io>
License-Expression: AGPL-3.0-or-later
Project-URL: Changelog, https://github.com/pyveci/supertask/blob/main/CHANGES.md
Project-URL: Documentation, https://supertask.readthedocs.io/
Project-URL: Issues, https://github.com/pyveci/supertask/issues
Project-URL: Repository, https://github.com/pyveci/supertask
Keywords: apscheduler,automation,cron,interval,jobs,recurrent,scheduler,scheduling,tasks,timetable,toolkit
Classifier: Development Status :: 1 - Planning
Classifier: Environment :: Console
Classifier: Intended Audience :: Customer Service
Classifier: Intended Audience :: Developers
Classifier: Intended Audience :: Education
Classifier: Intended Audience :: End Users/Desktop
Classifier: Intended Audience :: Information Technology
Classifier: Intended Audience :: Manufacturing
Classifier: Intended Audience :: Science/Research
Classifier: Intended Audience :: System Administrators
Classifier: Intended Audience :: Telecommunications Industry
Classifier: Operating System :: MacOS :: MacOS X
Classifier: Operating System :: Microsoft :: Windows
Classifier: Operating System :: POSIX :: Linux
Classifier: Operating System :: Unix
Classifier: Programming Language :: Python
Classifier: Programming Language :: Python :: 3 :: Only
Classifier: Programming Language :: Python :: 3.9
Classifier: Programming Language :: Python :: 3.10
Classifier: Programming Language :: Python :: 3.11
Classifier: Programming Language :: Python :: 3.12
Classifier: Programming Language :: Python :: 3.13
Classifier: Topic :: Adaptive Technologies
Classifier: Topic :: Communications
Classifier: Topic :: Database
Classifier: Topic :: Documentation
Classifier: Topic :: Education
Classifier: Topic :: Internet
Classifier: Topic :: Internet :: WWW/HTTP
Classifier: Topic :: Office/Business
Classifier: Topic :: Scientific/Engineering
Classifier: Topic :: Software Development :: Libraries
Classifier: Topic :: Software Development :: Pre-processors
Classifier: Topic :: Software Development :: Quality Assurance
Classifier: Topic :: Software Development :: Testing
Classifier: Topic :: Software Development :: Version Control
Classifier: Topic :: System :: Archiving
Classifier: Topic :: System :: Benchmark
Classifier: Topic :: System :: Clustering
Classifier: Topic :: System :: Distributed Computing
Classifier: Topic :: System :: Logging
Classifier: Topic :: System :: Monitoring
Classifier: Topic :: System :: Networking
Classifier: Topic :: System :: Systems Administration
Classifier: Topic :: Text Processing
Classifier: Topic :: Utilities
Requires-Python: >=3.9
License-File: LICENSE
Requires-Dist: apscheduler<4
Requires-Dist: click<9
Requires-Dist: colorama<0.5
Requires-Dist: colorlog<7
Requires-Dist: fastapi<0.116
Requires-Dist: halo<0.1
Requires-Dist: icecream<3
Requires-Dist: jinja2<4
Requires-Dist: markupsafe<4
Requires-Dist: pueblo[fileio]
Requires-Dist: pydantic<3
Requires-Dist: python-dotenv[cli]<2
Requires-Dist: python-multipart==0.0.20
Requires-Dist: pytz
Requires-Dist: sqlalchemy-cratedb==0.41.0
Requires-Dist: uvicorn<0.35
Requires-Dist: watchdog<7
Provides-Extra: develop
Requires-Dist: mypy<1.16; extra == "develop"
Requires-Dist: poethepoet<1; extra == "develop"
Requires-Dist: pyproject-fmt<3; extra == "develop"
Requires-Dist: ruff<0.12; extra == "develop"
Requires-Dist: validate-pyproject<1; extra == "develop"
Provides-Extra: release
Requires-Dist: build<2; extra == "release"
Requires-Dist: twine<7; extra == "release"
Provides-Extra: test
Requires-Dist: cratedb-toolkit==0.0.31; extra == "test"
Requires-Dist: httpx<0.29; extra == "test"
Requires-Dist: psycopg2-binary<3; extra == "test"
Requires-Dist: pytest<9; extra == "test"
Requires-Dist: pytest-cov<7; extra == "test"
Requires-Dist: pytest-mock<4; extra == "test"
Dynamic: license-file
